radd/CORE.py
radd/__init__.py
radd/build.py
radd/dfhandler.py
radd/models.py
radd/optimize.py
radd/theta.py
radd/vis.py
radd/adapt/RL.py
radd/adapt/__init__.py
radd/adapt/analyzer.py
radd/adapt/models_rl.py
radd/adapt/multirace.py
radd/adapt/visr.py
radd/compiled/__init__.py
radd/compiled/jitfx.py
radd/datasets/__init__.py
radd/datasets/eLife15/elife2015_example_data.csv
radd/datasets/eLife15/pro_stop_data.csv
radd/datasets/eLife15/re_stop_data.csv
radd/datasets/jNeuro18/adaptive_ss_behavior.csv
radd/docs/__init__.py
radd/docs/docs_draft.md
radd/docs/fit_report_docs.txt
radd/docs/xdpm_v_fit_report.txt
radd/docs/examples/__init__.py
radd/docs/examples/adaptiveDPM.png
radd/docs/examples/anim.mp4
radd/docs/examples/animations.py
radd/docs/examples/jneuro_task.png
radd/docs/examples/reactive_example_idx.csv
radd/styles/custom.css
radd/tools/__init__.py
radd/tools/analyze.py
radd/tools/colors.py
radd/tools/messages.py
radd/tools/utils.py
RADD-0.5.5.dist-info/LICENSE.txt
RADD-0.5.5.dist-info/METADATA
RADD-0.5.5.dist-info/WHEEL
RADD-0.5.5.dist-info/top_level.txt
RADD-0.5.5.dist-info/RECORD
