Metadata-Version: 2.1
Name: RADD
Version: 0.5.5
Summary: RADD (Race Against Drift-Diffusion model) is a python package for fitting & simulating cognitive models of reinforcement learning and decision-making
Home-page: http://github.com/CoAxLab/radd
Author: Kyle Dunovan, Timothy Verstynen, Jeremy Huang
Author-email: dunovank@gmail.com
License: UNKNOWN
Platform: UNKNOWN
Classifier: Environment :: Console
Classifier: Operating System :: OS Independent
Classifier: License :: OSI Approved :: BSD License
Classifier: Intended Audience :: Science/Research
Classifier: Development Status :: 3 - Alpha
Classifier: Programming Language :: Python
Classifier: Programming Language :: Python :: 2
Classifier: Programming Language :: Python :: 2.7
Classifier: Programming Language :: Python :: 3
Classifier: Programming Language :: Python :: 3.2
Classifier: Programming Language :: Python :: 3.4
Classifier: Programming Language :: Python :: 3.6
Classifier: Topic :: Scientific/Engineering
Requires-Dist: numpy (>=1.8.2)
Requires-Dist: scipy (>=0.16.1)
Requires-Dist: matplotlib (>=1.4.3)
Requires-Dist: seaborn (>=0.5.1)
Requires-Dist: pandas (>=0.15.1)
Requires-Dist: lmfit (>=0.9.1)
Requires-Dist: scikit-learn (>=0.17.1)
Requires-Dist: progressbar2 (>=3.9.3)
Requires-Dist: numba (>=0.30.1)
Requires-Dist: pyDOE
Requires-Dist: future
